ollama_agents/__init__.py
ollama_agents/agent.py
ollama_agents/caching.py
ollama_agents/context_manager.py
ollama_agents/ddg_search.py
ollama_agents/handoff.py
ollama_agents/logger.py
ollama_agents/mcp.py
ollama_agents/memory.py
ollama_agents/model_settings.py
ollama_agents/retry.py
ollama_agents/stats.py
ollama_agents/thinking.py
ollama_agents/tools.py
ollama_agents/tracing.py
ollama_agents/utils.py
ollama_agents/web_search.py
ollama_agents_sdk-0.2.0.dist-info/licenses/LICENSE
ollama_agents_sdk-0.2.0.dist-info/METADATA
ollama_agents_sdk-0.2.0.dist-info/WHEEL
ollama_agents_sdk-0.2.0.dist-info/top_level.txt
ollama_agents_sdk-0.2.0.dist-info/RECORD
