Metadata-Version: 2.4
Name: ollama-agents-sdk
Version: 0.2.0
Summary: Advanced Ollama agent framework with multi-agent collaboration
Home-page: https://github.com/SlyWolf1/ollama-agent
Author: Brian Manda
Author-email: Brian Manda <brianmanda44@gmail.com>
License: MIT
Project-URL: Homepage, https://github.com/SlyWolf1/ollama-agent
Project-URL: Documentation, https://github.com/SlyWolf1/ollama-agent#readme
Project-URL: Repository, https://github.com/SlyWolf1/ollama-agent
Project-URL: Issues, https://github.com/SlyWolf1/ollama-agent/issues
Keywords: ollama,agents,ai,llm,multi-agent,collaboration
Classifier: Development Status :: 4 - Beta
Classifier: Intended Audience :: Developers
Classifier: License :: OSI Approved :: MIT License
Classifier: Programming Language :: Python :: 3
Classifier: Programming Language :: Python :: 3.8
Classifier: Programming Language :: Python :: 3.9
Classifier: Programming Language :: Python :: 3.10
Classifier: Programming Language :: Python :: 3.11
Classifier: Programming Language :: Python :: 3.12
Requires-Python: >=3.8
License-File: LICENSE
Requires-Dist: ollama>=0.6.1
Requires-Dist: rich>=13.0.0
Requires-Dist: qdrant-client>=1.0.0
Requires-Dist: playwright>=1.40.0
Provides-Extra: dev
Requires-Dist: pytest>=6.0; extra == "dev"
Requires-Dist: pytest-asyncio>=0.21.0; extra == "dev"
Requires-Dist: pytest-cov>=4.0.0; extra == "dev"
Requires-Dist: black>=22.0.0; extra == "dev"
Requires-Dist: flake8>=5.0.0; extra == "dev"
Dynamic: author
Dynamic: home-page
Dynamic: license-file
Dynamic: requires-python
